{"gender":"Non-binary","location":{"street":{"number":4892,"name":"Kildeparken"},"city":"Sundby","state":"Nordjylland","country":"Denmark","postcode":32627,"coordinates":{"latitude":"-42.2969","longitude":"20.7375"},"timezone":{"offset":"-3:30","description":"Newfoundland"}},"username":"blackfrog996","dob":"1953-09-03T07:07:38.041Z","age":71,"picture":{"large":"https://randomuser.me/api/portraits/women/56.jpg","thumbnail":"https://randomuser.me/api/portraits/thumb/women/56.jpg"},"responses":{"whatBringsYouHere":"Exploring","idealRelationshipDynamic":"Short-term","preferredCommunication":"Text-heavy","attachmentStyle":"Avoidant","loveLanguage":"Quality Time","weekendActivity":"Traveling","petsPreference":"Love them & have one","dailyRoutine":"Flexible","conflictHandling":"Prefer to avoid conflict","biggestTurnOff":"Lack of ambition","wantKids":"Yes","workLifeBalance":"Flexible","biggestDealbreaker":"Incompatibility in beliefs","successInRelationship":"Growing together","uncompromisableValue":"Other","funFact":"I once hiked 10 miles barefoot","comfortFood":"Pasta","dreamLife":"Living in a cabin in the woods","guiltyPleasure":"Cheesy rom-coms","perfectFirstDate":"A spontaneous road trip","selfImprovement":"Becoming more confident","pastRelationshipLesson":"Love is not enough without respect","similarOrChallenge":"Someone who challenges me","liveAnywhere":"Switzerland for the nature and hiking","heartWinner":"Being kind to strangers"}}