{"gender":"Non-binary","location":{"street":{"number":6537,"name":"Brunnenstraße"},"city":"Schleswig","state":"Mecklenburg-Vorpommern","country":"Germany","postcode":58846,"coordinates":{"latitude":"-52.2542","longitude":"85.5834"},"timezone":{"offset":"-10:00","description":"Hawaii"}},"username":"lazyduck122","dob":"1983-01-23T22:17:55.748Z","age":42,"picture":{"large":"https://randomuser.me/api/portraits/women/64.jpg","thumbnail":"https://randomuser.me/api/portraits/thumb/women/64.jpg"},"responses":{"whatBringsYouHere":"Friendship","idealRelationshipDynamic":"Short-term","preferredCommunication":"Text-heavy","attachmentStyle":"Secure","loveLanguage":"Gifts","weekendActivity":"Other","petsPreference":"Not a fan","dailyRoutine":"Chill & spontaneous","conflictHandling":"Open to learning better ways","biggestTurnOff":"Poor communication","wantKids":"No","workLifeBalance":"Still figuring it out","biggestDealbreaker":"Lack of ambition","successInRelationship":"Shared experiences","uncompromisableValue":"Other","funFact":"I can juggle flaming torches","comfortFood":"Tacos","dreamLife":"Writing a book","guiltyPleasure":"K-pop","perfectFirstDate":"Stargazing in the mountains","selfImprovement":"Becoming more confident","pastRelationshipLesson":"Communication is everything","similarOrChallenge":"A mix of both","liveAnywhere":"Bali for the beaches and peace","heartWinner":"Making me laugh when I least expect it"}}