{"gender":"Male","location":{"street":{"number":7082,"name":"Lucenka"},"city":"Terebovlya","state":"Mikolayivska","country":"Ukraine","postcode":37565,"coordinates":{"latitude":"79.8047","longitude":"-131.0808"},"timezone":{"offset":"+5:30","description":"Bombay, Calcutta, Madras, New Delhi"}},"username":"organicpeacock975","dob":"1980-06-29T01:13:13.091Z","age":44,"picture":{"large":"https://randomuser.me/api/portraits/men/27.jpg","thumbnail":"https://randomuser.me/api/portraits/thumb/men/27.jpg"},"responses":{"whatBringsYouHere":"Casual Dating","idealRelationshipDynamic":"Open Relationship","preferredCommunication":"Slow to Respond but Thoughtful","attachmentStyle":"Secure","loveLanguage":"Acts of Service","weekendActivity":"Other","petsPreference":"Neutral","dailyRoutine":"Flexible","conflictHandling":"Open to learning better ways","biggestTurnOff":"Different political/social values","wantKids":"No","workLifeBalance":"More laid-back","biggestDealbreaker":"Lack of affection","successInRelationship":"Passion & chemistry","uncompromisableValue":"Other","funFact":"I can juggle flaming torches","comfortFood":"Sushi","dreamLife":"Writing a book","guiltyPleasure":"Reality TV","perfectFirstDate":"Exploring a new city together","selfImprovement":"Being more patient","pastRelationshipLesson":"Love is not enough without respect","similarOrChallenge":"A mix of both","liveAnywhere":"New York for the energy and opportunities","heartWinner":"Remembering small details about me"}}