{"gender":"Male","location":{"street":{"number":8094,"name":"Ash Dr"},"city":"Chesapeake","state":"Alaska","country":"United States","postcode":68956,"coordinates":{"latitude":"82.2632","longitude":"35.7619"},"timezone":{"offset":"+8:00","description":"Beijing, Perth, Singapore, Hong Kong"}},"username":"silverfrog406","dob":"1976-08-21T21:53:16.268Z","age":48,"picture":{"large":"https://randomuser.me/api/portraits/men/67.jpg","thumbnail":"https://randomuser.me/api/portraits/thumb/men/67.jpg"},"responses":{"whatBringsYouHere":"Casual Dating","idealRelationshipDynamic":"Short-term","preferredCommunication":"Mixed","attachmentStyle":"Avoidant","loveLanguage":"Gifts","weekendActivity":"Traveling","petsPreference":"Love them & have one","dailyRoutine":"Early bird","conflictHandling":"Open to learning better ways","biggestTurnOff":"Bad hygiene","wantKids":"No","workLifeBalance":"Flexible","biggestDealbreaker":"Lack of ambition","successInRelationship":"Passion & chemistry","uncompromisableValue":"Loyalty","funFact":"I have a secret talent for beatboxing","comfortFood":"Other","dreamLife":"Writing a book","guiltyPleasure":"Heavy metal","perfectFirstDate":"Exploring a new city together","selfImprovement":"Becoming more confident","pastRelationshipLesson":"Communication is everything","similarOrChallenge":"Someone similar to me","liveAnywhere":"Paris for the romance","heartWinner":"Bringing me my favorite snack without asking"}}