{"gender":"Female","location":{"street":{"number":3164,"name":"Hämeenkatu"},"city":"Vieremä","state":"Central Finland","country":"Finland","postcode":91978,"coordinates":{"latitude":"-21.9901","longitude":"-178.7591"},"timezone":{"offset":"+5:45","description":"Kathmandu"}},"username":"silverbear963","dob":"1995-04-18T15:07:11.499Z","age":29,"picture":{"large":"https://randomuser.me/api/portraits/women/41.jpg","thumbnail":"https://randomuser.me/api/portraits/thumb/women/41.jpg"},"responses":{"whatBringsYouHere":"Exploring","idealRelationshipDynamic":"Undecided","preferredCommunication":"Calls","attachmentStyle":"Avoidant","loveLanguage":"Acts of Service","weekendActivity":"Outdoors & Active","petsPreference":"Not a fan","dailyRoutine":"Flexible","conflictHandling":"Need space first","biggestTurnOff":"Lack of ambition","wantKids":"Yes","workLifeBalance":"Balanced","biggestDealbreaker":"Different lifestyles","successInRelationship":"Passion & chemistry","uncompromisableValue":"Personal Freedom","funFact":"I can juggle flaming torches","comfortFood":"Pasta","dreamLife":"Exploring outer space","guiltyPleasure":"K-pop","perfectFirstDate":"Stargazing in the mountains","selfImprovement":"Getting better at setting boundaries","pastRelationshipLesson":"Love is not enough without respect","similarOrChallenge":"Someone who challenges me","liveAnywhere":"Switzerland for the nature and hiking","heartWinner":"Bringing me my favorite snack without asking"}}