{"gender":"Male","location":{"street":{"number":5538,"name":"Avenue de la Libération"},"city":"Mulhouse","state":"Meuse","country":"France","postcode":85771,"coordinates":{"latitude":"-21.2351","longitude":"-6.5140"},"timezone":{"offset":"-12:00","description":"Eniwetok, Kwajalein"}},"username":"ticklishgorilla548","dob":"2000-08-02T06:52:02.365Z","age":24,"picture":{"large":"https://randomuser.me/api/portraits/men/86.jpg","thumbnail":"https://randomuser.me/api/portraits/thumb/men/86.jpg"},"responses":{"whatBringsYouHere":"Not Sure Yet","idealRelationshipDynamic":"Open Relationship","preferredCommunication":"Slow to Respond but Thoughtful","attachmentStyle":"Not Sure","loveLanguage":"Quality Time","weekendActivity":"Outdoors & Active","petsPreference":"Neutral","dailyRoutine":"Always on the go","conflictHandling":"Need space first","biggestTurnOff":"Poor communication","wantKids":"Yes","workLifeBalance":"More laid-back","biggestDealbreaker":"Incompatibility in beliefs","successInRelationship":"Growing together","uncompromisableValue":"Honesty","funFact":"I have a secret talent for beatboxing","comfortFood":"Pizza","dreamLife":"Living in a cabin in the woods","guiltyPleasure":"Old-school cartoons","perfectFirstDate":"Cooking a meal together","selfImprovement":"Getting better at setting boundaries","pastRelationshipLesson":"Compromise is key","similarOrChallenge":"Someone who challenges me","liveAnywhere":"New York for the energy and opportunities","heartWinner":"Bringing me my favorite snack without asking"}}